{
  "title": "Rango",
  "id": "186",
  "year": "2011",
  "url": "https://www.imdb.com/title/tt1192628/?ref_\u003dfn_tt_tt_1",
  "genreList": [
    "Animation",
    "Action",
    "Adventure"
  ],
  "countryList": [
    "United States",
    "United Kingdom"
  ],
  "description": "Rango is an ordinary chameleon who accidentally winds up in the town of Dirt, a lawless outpost in the Wild West in desperate need of a new sheriff.",
  "budget": "135,000,000",
  "gross": "245,724,603",
  "ratingValue": "7.3",
  "ratingCount": "293000",
  "duration": "107",
  "castList": [
    "Johnny Depp",
    "Isla Fisher",
    "Timothy Olyphant",
    "Abigail Breslin",
    "Ned Beatty",
    "Alfred Molina",
    "Bill Nighy",
    "Stephen Root",
    "Harry Dean Stanton",
    "Ray Winstone",
    "Ian Abercrombie",
    "Gil Birmingham",
    "James Ward Byrkit",
    "Claudia Black",
    "Blake Clark",
    "John Cothran",
    "Patrika Darbo",
    "George DelHoyo"
  ],
  "characterList": [
    "Rango",
    "Beans",
    "Spirit of the West",
    "Priscilla",
    "Mayor",
    "Roadkill",
    "Rattlesnake Jake",
    "Doc",
    "Balthazar",
    "Bad Bill",
    "Ambrose",
    "Wounded Bird",
    "Waffles",
    "Angelique",
    "Buford",
    "Elgin",
    "Delilah",
    "Señor Flan - Mariachi Accordion"
  ],
  "directorList": [
    "Gore Verbinski"
  ],
  "contentRating": "PG",
  "languageList": [
    "English"
  ],
  "userReviews": "498",
  "criticReviews": "367"
}