{
  "title": "The Chronicles of Riddick",
  "id": "242",
  "year": "2004",
  "url": "https://www.imdb.com/title/tt0296572/?ref_\u003dfn_tt_tt_1",
  "genreList": [
    "Action",
    "Adventure",
    "Sci-Fi"
  ],
  "countryList": [
    "United States"
  ],
  "description": "The wanted criminal Richard Bruno Riddick arrives on a planet called Helion Prime and finds himself up against an invading empire called the Necromongers, an army that plans to convert or ki... Read all",
  "budget": "105,000,000",
  "gross": "115,900,534",
  "ratingValue": "6.6",
  "ratingCount": "242000",
  "duration": "119",
  "castList": [
    "Vin Diesel",
    "Judi Dench",
    "Colm Feore",
    "Thandiwe Newton",
    "Karl Urban",
    "Alexa Davalos",
    "Linus Roache",
    "Yorick van Wageningen",
    "Nick Chinlund",
    "Keith David",
    "Mark Gibbon",
    "Roger Cross",
    "Terry Chen",
    "Christina Cox",
    "Nigel Vonas",
    "Shawn Reis",
    "Fabian Gujral",
    "Ty Olsson"
  ],
  "characterList": [
    "Riddick",
    "Aereon",
    "Lord Marshal",
    "Dame Vaako",
    "Vaako",
    "Kyra",
    "Purifier",
    "The Guv",
    "Toombs",
    "Imam",
    "Irgun",
    "Toal",
    "Merc Pilot",
    "Eve Logan",
    "Merc",
    "Merc",
    "Merc",
    "Merc"
  ],
  "directorList": [
    "David Twohy"
  ],
  "contentRating": "R",
  "languageList": [
    "English"
  ],
  "userReviews": "734",
  "criticReviews": "104"
}