{
  "title": "Trolls Band Together",
  "id": "247",
  "year": "2023",
  "url": "https://www.imdb.com/title/tt14362112/?ref_\u003dfn_tt_tt_1",
  "genreList": [
    "Animation",
    "Adventure",
    "Comedy"
  ],
  "countryList": [
    "United States"
  ],
  "description": "Poppy discovers that Branch was once part of the boy band \u0027BroZone\u0027 with his brothers, Floyd, John Dory, Spruce and Clay. When Floyd is kidnapped, Branch and Poppy embark on a journey to reu... Read all",
  "budget": "",
  "gross": "207,731,833",
  "ratingValue": "6.0",
  "ratingCount": "13000",
  "duration": "91",
  "castList": [
    "Anna Kendrick",
    "Justin Timberlake",
    "Kenan Thompson",
    "Walt Dohrn",
    "Anderson .Paak",
    "Ron Funches",
    "Kunal Nayyar",
    "David Fynn",
    "Kevin Michael Richardson",
    "Eric André",
    "Daveed Diggs",
    "Kid Cudi",
    "Troye Sivan",
    "Camila Cabello",
    "Zosia Mamet",
    "Amy Schumer",
    "Andrew Rannells",
    "Christopher Mintz-Plasse"
  ],
  "characterList": [
    "Poppy",
    "Branch",
    "Tiny Diamond",
    "King Peppy",
    "Prince D",
    "Cooper",
    "Guy Diamond",
    "Biggie",
    "Mr. Dinkles",
    "John Dory",
    "Spruce",
    "Clay",
    "Floyd",
    "Viva",
    "Crimp",
    "Velvet",
    "Veneer",
    "King Gristle"
  ],
  "directorList": [
    "Walt Dohrn",
    "Tim Heitz"
  ],
  "contentRating": "PG",
  "languageList": [
    "English",
    "Spanish"
  ],
  "userReviews": "100",
  "criticReviews": "74"
}