{
  "title": "The Magnificent Seven",
  "id": "384",
  "year": "2016",
  "url": "https://www.imdb.com/title/tt2404435/?ref_\u003dfn_tt_tt_1",
  "genreList": [
    "Action",
    "Adventure",
    "Drama"
  ],
  "countryList": [
    "United States",
    "Australia"
  ],
  "description": "Seven gunmen from a variety of backgrounds are brought together by a vengeful young widow to protect her town from the private army of a destructive industrialist.",
  "budget": "90,000,000",
  "gross": "162,360,695",
  "ratingValue": "6.9",
  "ratingCount": "228000",
  "duration": "132",
  "castList": [
    "Denzel Washington",
    "Chris Pratt",
    "Ethan Hawke",
    "Vincent D\u0027Onofrio",
    "Lee Byung-hun",
    "Manuel Garcia-Rulfo",
    "Martin Sensmeier",
    "Haley Bennett",
    "Peter Sarsgaard",
    "Luke Grimes",
    "Matt Bomer",
    "Jonathan Joss",
    "Cam Gigandet",
    "Emil Beheshti",
    "Mark Ashworth",
    "Billy Slaughter",
    "Dodge Prince",
    "Matthew Posey"
  ],
  "characterList": [
    "Chisolm",
    "Josh Faraday",
    "Goodnight Robicheaux",
    "Jack Horne",
    "Billy Rocks",
    "Vasquez",
    "Red Harvest",
    "Emma Cullen",
    "Bartholomew Bogue",
    "Teddy Q",
    "Matthew Cullen",
    "Denali",
    "McCann",
    "Maxwell",
    "Preacher",
    "Josiah",
    "Anthony",
    "Hank Stoner"
  ],
  "directorList": [
    "Antoine Fuqua"
  ],
  "contentRating": "PG-13",
  "languageList": [
    "English",
    "North American Indian",
    "Spanish"
  ],
  "userReviews": "614",
  "criticReviews": "396"
}