{
  "title": "Happy Feet",
  "id": "412",
  "year": "2006",
  "url": "https://www.imdb.com/title/tt0366548/?ref_\u003dfn_tt_tt_1",
  "genreList": [
    "Animation",
    "Adventure",
    "Comedy"
  ],
  "countryList": [
    "United States",
    "Australia"
  ],
  "description": "Into the world of the Emperor Penguins, who find their soul mates through song, a penguin is born who cannot sing. But he can tap dance something fierce!",
  "budget": "100,000,000",
  "gross": "384,336,108",
  "ratingValue": "6.4",
  "ratingCount": "200000",
  "duration": "108",
  "castList": [
    "Elijah Wood",
    "Brittany Murphy",
    "Hugh Jackman",
    "Robin Williams",
    "Carlos Alazraqui",
    "Lombardo Boyar",
    "Jeffrey Garcia",
    "Johnny A. Sanchez",
    "Nicole Kidman",
    "Hugo Weaving",
    "Elizabeth Daily",
    "Magda Szubanski",
    "Miriam Margolyes",
    "Fat Joe",
    "Alyssa Shafer",
    "Cesar Flores",
    "Anthony LaPaglia",
    "Danny Mann"
  ],
  "characterList": [
    "Mumble",
    "Gloria",
    "Memphis",
    "Ramon",
    "Nestor",
    "Raul",
    "Rinaldo",
    "Lombardo",
    "Norma Jean",
    "Noah the Elder",
    "Baby Mumble",
    "Miss Viola",
    "Mrs. Astrakhan",
    "Seymour",
    "Baby Gloria",
    "Baby Seymour",
    "Boss Skua",
    "Dino"
  ],
  "directorList": [
    "George Miller",
    "Warren Coleman",
    "Judy Morris"
  ],
  "contentRating": "PG",
  "languageList": [
    "English"
  ],
  "userReviews": "624",
  "criticReviews": "124"
}