{
  "title": "The Chronicles of Narnia: The Voyage of the Dawn Treader",
  "id": "115",
  "year": "2010",
  "url": "https://www.imdb.com/title/tt0980970/?ref_\u003dfn_tt_tt_1",
  "genreList": [
    "Adventure",
    "Family",
    "Fantasy"
  ],
  "countryList": [
    "United States",
    "United Kingdom",
    "Canada",
    "Australia",
    "Germany"
  ],
  "description": "Lucy and Edmund Pevensie return to Narnia with their cousin Eustace where they meet up with Prince Caspian for a trip across the sea aboard the royal ship The Dawn Treader. Along the way the... Read all",
  "budget": "155,000,000",
  "gross": "415,686,217",
  "ratingValue": "6.3",
  "ratingCount": "166000",
  "duration": "113",
  "castList": [
    "Ben Barnes",
    "Skandar Keynes",
    "Georgie Henley",
    "Will Poulter",
    "Gary Sweet",
    "Terry Norris",
    "Bruce Spence",
    "Bille Brown",
    "Laura Brent",
    "Colin Moody",
    "Tilda Swinton",
    "Anna Popplewell",
    "William Moseley",
    "Shane Rangi",
    "Arthur Angel",
    "Arabella Morton",
    "Rachel Blakely",
    "Steven Rooke"
  ],
  "characterList": [
    "Caspian",
    "Edmund Pevensie",
    "Lucy Pevensie",
    "Eustace Scrubb",
    "Drinian",
    "Lord Bern",
    "Lord Rhoop",
    "Coriakin",
    "Liliandil",
    "Auctioneer",
    "The White Witch",
    "Susan Pevensie",
    "Peter Pevensie",
    "Tavros",
    "Rhince",
    "Gael",
    "Gael\u0027s Mum",
    "Faun"
  ],
  "directorList": [
    "Michael Apted"
  ],
  "contentRating": "PG",
  "languageList": [
    "English"
  ],
  "userReviews": "270",
  "criticReviews": "217"
}