{
  "title": "Charlie and the Chocolate Factory",
  "id": "127",
  "year": "2005",
  "url": "https://www.imdb.com/title/tt0367594/?ref_\u003dfn_tt_tt_1",
  "genreList": [
    "Adventure",
    "Comedy",
    "Family"
  ],
  "countryList": [
    "United States",
    "United Kingdom"
  ],
  "description": "Charlie, a young boy from an impoverished family, and four other kids win a tour of an amazing chocolate factory run by an imaginative chocolatier, Willy Wonka, and his staff of Oompa-Loompa... Read all",
  "budget": "150,000,000",
  "gross": "474,968,763",
  "ratingValue": "6.7",
  "ratingCount": "529000",
  "duration": "115",
  "castList": [
    "Johnny Depp",
    "Freddie Highmore",
    "David Kelly",
    "Helena Bonham Carter",
    "Noah Taylor",
    "Missi Pyle",
    "James Fox",
    "Deep Roy",
    "Christopher Lee",
    "Adam Godley",
    "Franziska Troegner",
    "AnnaSophia Robb",
    "Julia Winter",
    "Jordan Fry",
    "Philip Wiegratz",
    "Blair Dunlop",
    "Liz Smith",
    "Eileen Essell"
  ],
  "characterList": [
    "Willy Wonka",
    "Charlie Bucket",
    "Grandpa Joe",
    "Mrs. Bucket",
    "Mr. Bucket",
    "Mrs. Beauregarde",
    "Mr. Salt",
    "Oompa Loompa",
    "Dr. Wonka",
    "Mr. Teavee",
    "Mrs. Gloop",
    "Violet Beauregarde",
    "Veruca Salt",
    "Mike Teavee",
    "Augustus Gloop",
    "Little Willy Wonka",
    "Grandma Georgina",
    "Grandma Josephine"
  ],
  "directorList": [
    "Tim Burton"
  ],
  "contentRating": "PG",
  "languageList": [
    "English"
  ],
  "userReviews": "1500",
  "criticReviews": "271"
}