{
  "title": "Spider-Man 2",
  "id": "38",
  "year": "2004",
  "url": "https://www.imdb.com/title/tt0316654/?ref_\u003dfn_tt_tt_1",
  "genreList": [
    "Action",
    "Adventure",
    "Sci-Fi"
  ],
  "countryList": [
    "United States"
  ],
  "description": "Peter Parker is beset with troubles in his failing personal life as he battles a former brilliant scientist named Otto Octavius.",
  "budget": "200,000,000",
  "gross": "788,976,453",
  "ratingValue": "7.5",
  "ratingCount": "708000",
  "duration": "127",
  "castList": [
    "Tobey Maguire",
    "Kirsten Dunst",
    "Alfred Molina",
    "James Franco",
    "Rosemary Harris",
    "J.K. Simmons",
    "Donna Murphy",
    "Daniel Gillies",
    "Dylan Baker",
    "Bill Nunn",
    "Vanessa Ferlito",
    "Aasif Mandvi",
    "Willem Dafoe",
    "Cliff Robertson",
    "Ted Raimi",
    "Elizabeth Banks",
    "Bruce Campbell",
    "Gregg Edelman"
  ],
  "characterList": [
    "Spider-Man",
    "Mary Jane Watson",
    "Doc Ock",
    "Harry Osborn",
    "May Parker",
    "J. Jonah Jameson",
    "Rosalie Octavius",
    "John Jameson",
    "Dr. Curt Connors",
    "Joseph \u0027Robbie\u0027 Robertson",
    "Louise",
    "Mr. Aziz",
    "Green Goblin",
    "Ben Parker",
    "Hoffman",
    "Miss Brant",
    "Snooty Usher",
    "Dr. Davis"
  ],
  "directorList": [
    "Sam Raimi"
  ],
  "contentRating": "PG-13",
  "languageList": [
    "English",
    "Russian",
    "Chinese"
  ],
  "userReviews": "1600",
  "criticReviews": "335"
}