{
  "title": "Divergent",
  "id": "418",
  "year": "2014",
  "url": "https://www.imdb.com/title/tt1840309/?ref_\u003dfn_tt_tt_1",
  "genreList": [
    "Action",
    "Adventure",
    "Mystery"
  ],
  "countryList": [
    "United States"
  ],
  "description": "In a world divided by factions based on virtues, Tris learns she\u0027s Divergent and won\u0027t fit in. When she discovers a plot to destroy Divergents, Tris and the mysterious Four must find out wha... Read all",
  "budget": "85,000,000",
  "gross": "288,885,818",
  "ratingValue": "6.6",
  "ratingCount": "489000",
  "duration": "139",
  "castList": [
    "Shailene Woodley",
    "Theo James",
    "Kate Winslet",
    "Jai Courtney",
    "Ashley Judd",
    "Ray Stevenson",
    "Zoë Kravitz",
    "Miles Teller",
    "Tony Goldwyn",
    "Ansel Elgort",
    "Maggie Q",
    "Mekhi Phifer",
    "Ben Lloyd-Hughes",
    "Christian Madsen",
    "Amy Newbold",
    "Ben Lamb",
    "Janet Ulrich Brooks",
    "Clara Burger"
  ],
  "characterList": [
    "Tris",
    "Four",
    "Jeanine",
    "Eric",
    "Natalie",
    "Marcus",
    "Christina",
    "Peter",
    "Andrew",
    "Caleb",
    "Tori",
    "Max",
    "Will",
    "Al",
    "Molly",
    "Edward",
    "Erudite Teacher",
    "Little Abnegation Girl"
  ],
  "directorList": [
    "Neil Burger"
  ],
  "contentRating": "PG-13",
  "languageList": [
    "English",
    "Spanish"
  ],
  "userReviews": "893",
  "criticReviews": "438"
}