{
  "title": "The 6th Day",
  "id": "455",
  "year": "2000",
  "url": "https://www.imdb.com/title/tt0216216/?ref_\u003dfn_tt_tt_1",
  "genreList": [
    "Action",
    "Mystery",
    "Sci-Fi"
  ],
  "countryList": [
    "United States"
  ],
  "description": "A man meets a clone of himself and stumbles into a grand conspiracy about clones taking over the world.",
  "budget": "82,000,000",
  "gross": "96,085,477",
  "ratingValue": "5.9",
  "ratingCount": "128000",
  "duration": "123",
  "castList": [
    "Arnold Schwarzenegger",
    "Michael Rapaport",
    "Tony Goldwyn",
    "Michael Rooker",
    "Sarah Wynter",
    "Wendy Crewson",
    "Rodney Rowland",
    "Terry Crews",
    "Ken Pogue",
    "Colin Cunningham",
    "Robert Duvall",
    "Wanda Cannon",
    "Taylor Reid",
    "Jennifer Gareis",
    "Don McManus",
    "Steve Bacic",
    "Christopher Lawford",
    "Mark Brandon"
  ],
  "characterList": [
    "Adam Gibson",
    "Hank Morgan",
    "Michael Drucker",
    "Robert Marshall",
    "Talia Elsworth",
    "Natalie Gibson",
    "P. Wiley",
    "Vincent",
    "Speaker Day",
    "Tripp",
    "Dr. Griffin Weir",
    "Katherine Weir",
    "Clara Gibson",
    "Virtual Girlfriend",
    "RePet Salesman",
    "Johnny Phoenix",
    "Police Lieutenant",
    "RePet Spokesman"
  ],
  "directorList": [
    "Roger Spottiswoode"
  ],
  "contentRating": "PG-13",
  "languageList": [
    "English"
  ],
  "userReviews": "348",
  "criticReviews": "123"
}