{
  "title": "Singularity",
  "id": "86",
  "year": "2017",
  "url": "https://www.imdb.com/title/tt7312940/?ref_\u003dfn_tt_tt_1",
  "genreList": [
    "Action",
    "Adventure",
    "Drama"
  ],
  "countryList": [
    "Switzerland",
    "United States"
  ],
  "description": "Earth 2020, 3/4 of it\u0027s households have a robot. The AI supercomputer, Kronos, considers humans the biggest threat to Earth. A century later, few humans are left. Calia seeks the last human ... Read all",
  "budget": "",
  "gross": "86,822",
  "ratingValue": "3.6",
  "ratingCount": "12000",
  "duration": "92",
  "castList": [
    "Julian Schaffner",
    "John Cusack",
    "Carmen Argenziano",
    "Eileen Grubba",
    "Jeannine Michèle Wacker",
    "Pavlo Bubryak",
    "Paul American",
    "David Chrisman",
    "Hrncir Kuba",
    "Elisa Dvorakova",
    "Oliver Czavar",
    "Michelle Michaels",
    "Jason Marnocha",
    "Elaine Loh",
    "Ego Nwodim",
    "Philipp Borchhardt",
    "Olga Danielova",
    "Daniel Kafka"
  ],
  "characterList": [
    "Andrew Davis",
    "Elias Van Dorne",
    "Damien Walsh",
    "Veronica Davis",
    "Calia",
    "Cassiem",
    "Bus Driver",
    "TV Reporter",
    "Boy",
    "Girl",
    "Cassiem",
    "UI",
    "Minions",
    "Reporter",
    "Assistant",
    "Bandit",
    "Bandit",
    "Bandit"
  ],
  "directorList": [
    "Robert Kouba"
  ],
  "contentRating": "PG-13",
  "languageList": [
    "English"
  ],
  "userReviews": "364",
  "criticReviews": "18"
}